{
    "12336":  "Grande Île aux Cawottes",
    "3589":  "Petite île Brakmarienne",
    "32606":  "Île Ten'Dau",
    "34890":  "Grande île Brakmarienne",
    "7171":  "Petit Îlot Boisé",
    "83096":  "Petite île Sufokienne",
    "36857":  "Île du Naufragé",
    "543340":  "Petite Île Bontarienne",
    "57419":  "Petite île Amaknéenne",
    "2307":  "Grande île Bontarienne",
    "81171":  "Petite Île aux Cawottes",
    "22554":  "Île Brakmarienne moyenne",
    "81436":  "Petite Île Bontarienne",
    "12104":  "Bateau Amakna 01",
    "57858":  "Bateau Amakna 02",
    "1949":  "Bateau Amakna 03",
    "87155":  "Bateau Cochon 01",
    "15163":  "Bateau Cochon 02",
    "86048":  "Bateau Cochon 03",
    "17183":  "Bateau Chafer 01",
    "96106":  "Bateau Chafer 02",
    "49609":  "Bateau Chafer 03",
    "77727":  "Bateau Mino 01",
    "71716":  "Bateau Mino 02",
    "60755":  "Bateau Mino 03"
}